flask_auth_wrapper/__init__.py
flask_auth_wrapper/auth.py
flask_auth_wrapper/config.py
flask_auth_wrapper/decorators.py
flask_auth_wrapper/exceptions.py
flask_auth_wrapper/utils.py
flask_auth_wrapper/models/__init__.py
flask_auth_wrapper/models/auth_providers_model.py
flask_auth_wrapper/models/tokens_model.py
flask_auth_wrapper/models/user_auth_providers_model.py
flask_auth_wrapper/models/users_model.py
flask_auth_wrapper/services/__init__.py
flask_auth_wrapper/services/services.py
flask_oauth_guard-0.0.87.dist-info/LICENSE
flask_oauth_guard-0.0.87.dist-info/METADATA
flask_oauth_guard-0.0.87.dist-info/WHEEL
flask_oauth_guard-0.0.87.dist-info/top_level.txt
flask_oauth_guard-0.0.87.dist-info/RECORD
